task_manager_saqib/__init__.py
task_manager_saqib-1.0.7.dist-info/METADATA
task_manager_saqib-1.0.7.dist-info/WHEEL
task_manager_saqib-1.0.7.dist-info/top_level.txt
task_manager_saqib-1.0.7.dist-info/RECORD
