Metadata-Version: 2.4
Name: task-manager-saqib
Version: 1.0.7
Summary: A simple Python task manager library for adding, removing, and updating tasks.
Home-page: https://pypi.org/project/task-manager-saqib/
Author: Saqib Raheem(ws)
Author-email: wsssaqib99@gmail.com
Requires-Python: >=3.6
Dynamic: author
Dynamic: author-email
Dynamic: description
Dynamic: description-content-type
Dynamic: home-page
Dynamic: requires-python
Dynamic: summary
